latex_generator_evgenfosgen/__init__.py
latex_generator_evgenfosgen/generator.py
latex_generator_evgenfosgen-0.1.1.dist-info/METADATA
latex_generator_evgenfosgen-0.1.1.dist-info/WHEEL
latex_generator_evgenfosgen-0.1.1.dist-info/RECORD
