Metadata-Version: 2.4
Name: latex_generator_evgenfosgen
Version: 0.1.1
Summary: A simple LaTeX generator for tables and images
Author-email: Evgenij <123@email.com>
